statjax/__init__.py
statjax/causal.py
statjax/core.py
statjax/metrics.py
statjax/nn.py
statjax/probability.py
statjax/tables.py
statjax/util.py
statjax/glm/__init__.py
statjax/glm/bayes.py
statjax/glm/canonical.py
statjax/glm/glm.py
statjax/glm/links.py
statjax-0.0.8.dist-info/LICENSE
statjax-0.0.8.dist-info/METADATA
statjax-0.0.8.dist-info/WHEEL
statjax-0.0.8.dist-info/top_level.txt
statjax-0.0.8.dist-info/RECORD
