Metadata-Version: 2.1
Name: statjax
Version: 0.0.8
Summary: Data science tools built with a Jax backend.
Author: Sam Jones
Classifier: Programming Language :: Python :: 3
Classifier: License :: OSI Approved :: MIT License
Classifier: Operating System :: OS Independent
Requires-Python: >=3.11
License-File: LICENSE
Requires-Dist: jax
Requires-Dist: jaxlib
Requires-Dist: oryx
Requires-Dist: optax
Requires-Dist: formulaic
Requires-Dist: numpy <2.0.0
Requires-Dist: pandas
